Metadata-Version: 1.0
Name: gaubin-pdf
Version: 0.1
Summary: Gaussian distributions
Home-page: UNKNOWN
Author: Paima Marbun
Author-email: something@email.com
License: UNKNOWN
Platform: UNKNOWN
